flaskconstructicon/__init__.py
flaskconstructicon/__main__.py
flaskconstructicon/resources/__init__.py
flaskconstructicon/resources/help.txt
flaskconstructicon/resources/test.txt
flaskconstructicon/resources/database_configs/mysqlconnection.txt
flaskconstructicon/resources/models/test1
flaskconstructicon/resources/models/test2
flaskconstructicon/resources/patterns/CD_MVC.json
flaskconstructicon-1.0.9.dist-info/METADATA
flaskconstructicon-1.0.9.dist-info/WHEEL
flaskconstructicon-1.0.9.dist-info/licenses/LICENSE
flaskconstructicon-1.0.9.dist-info/RECORD
