Metadata-Version: 2.1
Name: FlaskConstructicon
Version: 1.0.9
Summary: A package for building Flask Projects
Project-URL: Homepage, https://github.com/Stuart-Yee/FlaskConstructicon
Project-URL: Bug Tracker, https://github.com/Stuart-Yee/FlaskConstructicon
Author-email: Stuart Yee <ki6fzb@gmail.com>
License:  GNU GENERAL PUBLIC LICENSE
Classifier: License :: OSI Approved :: GNU General Public License v3 (GPLv3)
Classifier: Operating System :: OS Independent
Classifier: Programming Language :: Python :: 3
Requires-Python: >=3.7
